{
	"textures": {
		"leaves": "gourmet:block/bush/bush_base",
		"particle": "gourmet:block/bush/bush_base"
	},
	"elements": [
		{
			"name": "cube",
			"from": [5, 0, 5],
			"to": [11, 6, 11],
			"shade": true,
			"faces": {
				"north": {"uv": [0, 0, 6, 6], "texture": "#leaves"},
				"east": {"uv": [0, 0, 6, 6], "texture": "#leaves"},
				"south": {"uv": [0, 0, 6, 6], "texture": "#leaves"},
				"west": {"uv": [0, 0, 6, 6], "texture": "#leaves"},
				"up": {"uv": [0, 0, 6, 6], "texture": "#leaves"},
				"down": {"uv": [0, 0, 6, 6], "texture": "#leaves"}
			}
		}
	]
}